pylsp_ruff/__init__.py
pylsp_ruff/plugin.py
pylsp_ruff/ruff.py
pylsp_ruff/settings.py
python_lsp_ruff-2.2.2.dist-info/LICENSE
python_lsp_ruff-2.2.2.dist-info/METADATA
python_lsp_ruff-2.2.2.dist-info/WHEEL
python_lsp_ruff-2.2.2.dist-info/entry_points.txt
python_lsp_ruff-2.2.2.dist-info/top_level.txt
python_lsp_ruff-2.2.2.dist-info/RECORD
