Metadata-Version: 2.1
Name: python-lsp-ruff
Version: 2.2.2
Summary: Ruff linting plugin for pylsp
Author-email: Julian Hossbach <julian.hossbach@gmx.de>
License: MIT
Project-URL: Homepage, https://github.com/python-lsp/python-lsp-ruff
Project-URL: Bug Tracker, https://github.com/python-lsp/python-lsp-ruff/issues
Requires-Python: >=3.8
License-File: LICENSE
Requires-Dist: ruff >=0.2.0
Requires-Dist: python-lsp-server
Requires-Dist: cattrs !=23.2.1
Requires-Dist: lsprotocol >=2023.0.1
Requires-Dist: tomli >=1.1.0 ; python_version < "3.11"
Provides-Extra: dev
Requires-Dist: pytest ; extra == 'dev'
Requires-Dist: pre-commit ; extra == 'dev'
